finRav/__init__.py
finRav/py.typed
finRav/stats/__init__.py
finRav/stats/detrended_fluctuation_analysis.py
finRav/stoch/__init__.py
finRav/stoch/_davies_harte_method.py
finRav/stoch/_fbm_base.py
finRav/stoch/_fractional_gaussian_noise.py
finRav/stoch/_hosking_method.py
finRav/stoch/fractional_brownian_motion.py
finrav-0.3.2.dist-info/METADATA
finrav-0.3.2.dist-info/WHEEL
finrav-0.3.2.dist-info/licenses/LICENSE
finrav-0.3.2.dist-info/RECORD
