Metadata-Version: 2.4
Name: finRav
Version: 0.3.2
Summary: Financial stochastic processes and statistical tools
Project-URL: Homepage, https://github.com/ravivherrera/finRav
Project-URL: Issues, https://github.com/ravivherrera/finRav/issues
Author: Raviv Rafael Herrera
License: MIT
License-File: LICENSE
Requires-Python: >=3.9
Requires-Dist: matplotlib>=3.8
Requires-Dist: numpy>=1.23
Requires-Dist: pandas>=2.0
Requires-Dist: scipy>=1.10
